[
    {
        "levelNo": 1,
        "silverPercentage": 10,
        "goldPercentage": 15,
        "platinumPercentage": 20
    },
    {
        "levelNo": 2,
        "silverPercentage": 4,
        "goldPercentage": 4,
        "platinumPercentage": 4
    },
    {
        "levelNo": 3,
        "silverPercentage": 3,
        "goldPercentage": 3,
        "platinumPercentage": 3
    },
    {
        "levelNo": 4,
        "silverPercentage": 1,
        "goldPercentage": 1,
        "platinumPercentage": 1
    },
    {
        "levelNo": 5,
        "silverPercentage": 1,
        "goldPercentage": 1,
        "platinumPercentage": 1
    },
    {
        "levelNo": 6,
        "silverPercentage": 0.5,
        "goldPercentage": 0.5,
        "platinumPercentage": 0.5
    },
    {
        "levelNo": 7,
        "silverPercentage": 0.5,
        "goldPercentage": 0.5,
        "platinumPercentage": 0.5
    },
    {
        "levelNo": 8,
        "silverPercentage": 0,
        "goldPercentage": 0.5,
        "platinumPercentage": 0.5
    },
    {
        "levelNo": 9,
        "silverPercentage": 0,
        "goldPercentage": 0.5,
        "platinumPercentage": 0.5
    },
    {
        "levelNo": 10,
        "silverPercentage": 0,
        "goldPercentage": 0.5,
        "platinumPercentage": 0.5
    },
    {
        "levelNo": 11,
        "silverPercentage": 0,
        "goldPercentage": 0,
        "platinumPercentage": 0.25
    },
    {
        "levelNo": 12,
        "silverPercentage": 0,
        "goldPercentage": 0,
        "platinumPercentage": 0.25
    }
]